ipyleaflet_legend/__init__.py
ipyleaflet_legend/_version.py
ipyleaflet_legend/legend.py
ipyleaflet_legend/static/056dcd0b0dea7c78019243311551d64b.png
ipyleaflet_legend/static/07f16cd155661436fe27959eab15c820.png
ipyleaflet_legend/static/0b50583aa1b8ff230b57b92263e47a3e.png
ipyleaflet_legend/static/0f2c10250081cf1bd9a4d2250b80dba6.png
ipyleaflet_legend/static/2273e3d8ad9264b7daa5bdbf8e6b47f8.png
ipyleaflet_legend/static/35ae4b5f1bf198c6d955618b85710d05.png
ipyleaflet_legend/static/401d815dc206b8dc1b17cd0e37695975.png
ipyleaflet_legend/static/44a526eed258222515aa21eaffd14a96.png
ipyleaflet_legend/static/473ee081160a469c95199d70e78f55fa.png
ipyleaflet_legend/static/4f0283c6ce28e888000e978e537a6a56.png
ipyleaflet_legend/static/592b7360116d244f9dd932b0c0041982.png
ipyleaflet_legend/static/69fbc9c24b3665b801445c9bccc7017d.png
ipyleaflet_legend/static/6a1e950d14904d4b6fb5c9bdc3dfad06.png
ipyleaflet_legend/static/6e8e462555c4b10dbfbc206e8276e6e2.png
ipyleaflet_legend/static/7910c667cb5ddcdcb4ee3278627c85e1.png
ipyleaflet_legend/static/79148a43587cbe5c43d24fa894a78ba3.png
ipyleaflet_legend/static/994ef255f2077b24b0d8975e90e37a33.png
ipyleaflet_legend/static/9e9c77db241e8a58da99bf28694c907d.png
ipyleaflet_legend/static/a6137456ed160d7606981aa57c559898.png
ipyleaflet_legend/static/cfe6f6ffc5b2d6c482c36c68522f0282.png
ipyleaflet_legend/static/d3a5d64a8534322988a4bed1b7dbc8b0.png
ipyleaflet_legend/static/ddb8362e333c8f3225da9d578d00c14c.png
ipyleaflet_legend/static/deac1d4aa2ccf7ed832e4db55bb64e63.png
ipyleaflet_legend/static/e81afdf0b23bc88ea3e6ef3fc2fb65d6.png
ipyleaflet_legend/static/extension.js
ipyleaflet_legend/static/f4b0c949877c5f94158208551a57e29d.png
ipyleaflet_legend/static/fd48ced8485c638cadcea3eaab6d0937.png
ipyleaflet_legend/static/fd5728f2cf777b06b966d05c0c823dc9.svg
ipyleaflet_legend/static/index.js
ipyleaflet_legend/static/index.js.map
ipyleaflet_legend-0.1.0.data/data/etc/jupyter/nbconfig/notebook.d/ipyleaflet-legend.json
ipyleaflet_legend-0.1.0.dist-info/LICENSE
ipyleaflet_legend-0.1.0.dist-info/METADATA
ipyleaflet_legend-0.1.0.dist-info/WHEEL
ipyleaflet_legend-0.1.0.dist-info/top_level.txt
ipyleaflet_legend-0.1.0.dist-info/RECORD
